aftermarketpl/__init__.py
aftermarketpl-0.1.3.dist-info/LICENSE
aftermarketpl-0.1.3.dist-info/METADATA
aftermarketpl-0.1.3.dist-info/WHEEL
aftermarketpl-0.1.3.dist-info/top_level.txt
aftermarketpl-0.1.3.dist-info/RECORD
