Metadata-Version: 2.1
Name: aftermarketpl
Version: 0.1.3
Summary: Interface for the AfterMarket.pl API
Home-page: UNKNOWN
Author: UNKNOWN
Author-email: UNKNOWN
License: UNKNOWN
Platform: UNKNOWN
Requires-Dist: requests (>=2.20.0)
